Metadata-Version: 2.1
Name: datallia
Version: 0.1.1
Summary: Simple data structure library with suitable __repr__ methods
Home-page: UNKNOWN
Author: Pablo Florindo
Author-email: pabloflogon@gmail.com
License: MIT
Platform: UNKNOWN
License-File: LICENSE
